plantable/__init__.py
plantable/const.py
plantable/scripts.py
plantable/templates.py
plantable/utils.py
plantable/client/__init__.py
plantable/client/account.py
plantable/client/admin.py
plantable/client/conf.py
plantable/client/core.py
plantable/client/exception.py
plantable/client/user.py
plantable/client/base/__init__.py
plantable/client/base/base.py
plantable/client/base/builtin.py
plantable/model/__init__.py
plantable/model/account.py
plantable/model/column.py
plantable/model/core.py
plantable/model/event.py
plantable/model/form.py
plantable/serde/__init__.py
plantable/serde/deserializer/__init__.py
plantable/serde/deserializer/deserializer.py
plantable/serde/deserializer/to_avro.py
plantable/serde/deserializer/to_postgres.py
plantable/serde/deserializer/to_python.py
plantable/serde/serializer/__init__.py
plantable/serde/serializer/from_arrow.py
plantable/serde/serializer/from_python.py
plantable/server/__init__.py
plantable/server/app.py
plantable/server/conf.py
plantable/server/util.py
plantable/server/router/__init__.py
plantable/server/router/api_token.py
plantable/server/router/user.py
plantable/static/__init__.py
plantable-2024.7.6.dist-info/METADATA
plantable-2024.7.6.dist-info/WHEEL
plantable-2024.7.6.dist-info/entry_points.txt
plantable-2024.7.6.dist-info/top_level.txt
plantable-2024.7.6.dist-info/RECORD
